tatsu_api/__init__.py
tatsu_api/client.py
tatsu_api/enums.py
tatsu_api/errors.py
tatsu_api/http.py
tatsu_api/models.py
tatsu_api/py.typed
tatsu_api-1.0.0.post1.dist-info/LICENSE
tatsu_api-1.0.0.post1.dist-info/METADATA
tatsu_api-1.0.0.post1.dist-info/WHEEL
tatsu_api-1.0.0.post1.dist-info/top_level.txt
tatsu_api-1.0.0.post1.dist-info/RECORD
