Metadata-Version: 2.1
Name: tatsu-api
Version: 1.0.0.post1
Summary: An unofficial, async-ready wrapper for the Tatsu API.
Author-email: Sachaa-Thanasius <111999343+Sachaa-Thanasius@users.noreply.github.com>
License: MIT License
Project-URL: Homepage, https://github.com/Sachaa-Thanasius/tatsu-api
Project-URL: Bug Tracker, https://github.com/Sachaa-Thanasius/tatsu-api/issues
Keywords: python,python-3,tatsu,tatsu-api
Classifier: Development Status :: 3 - Alpha
Classifier: Framework :: aiohttp
Classifier: License :: OSI Approved :: MIT License
Classifier: Natural Language :: English
Classifier: Operating System :: OS Independent
Classifier: Programming Language :: Python :: 3 :: Only
Classifier: Programming Language :: Python :: 3.8
Classifier: Programming Language :: Python :: 3.9
Classifier: Programming Language :: Python :: 3.10
Classifier: Programming Language :: Python :: 3.11
Classifier: Topic :: Internet
Classifier: Topic :: Software Development :: Libraries
Classifier: Topic :: Software Development :: Libraries :: Python Modules
Classifier: Topic :: Utilities
Classifier: Typing :: Typed
Requires-Python: >=3.8
License-File: LICENSE
Requires-Dist: aiohttp >=3.8
Requires-Dist: msgspec
Provides-Extra: speed
Requires-Dist: aiodns >=1.1 ; extra == 'speed'
Requires-Dist: Brotli ; extra == 'speed'
Requires-Dist: cchardet ; extra == 'speed'
